deepdraughts/__init__.py
deepdraughts/game_collector.py
deepdraughts/gui.py
deepdraughts/mcts_alphazero.py
deepdraughts/mcts_pure.py
deepdraughts/net_pytorch.py
deepdraughts/train_pipline.py
deepdraughts/endgame/__init__.py
deepdraughts/endgame/generator.py
deepdraughts/env/__init__.py
deepdraughts/env/cython_env/__init__.py
deepdraughts/env/cython_env/env_utils.py
deepdraughts/env/cython_env/setup.py
deepdraughts/env/py_env/__init__.py
deepdraughts/env/py_env/board.py
deepdraughts/env/py_env/env_utils.py
deepdraughts/env/py_env/game.py
deepdraughts/env/py_env/io_utils.py
deepdraughts/env/py_env/piece.py
deepdraughts-1.2.0.data/data/resources/endgame1p.pkl
deepdraughts-1.2.0.data/data/resources/endgame2p.pkl
deepdraughts-1.2.0.data/data/resources/endgame3p.pkl
deepdraughts-1.2.0.data/data/resources/endgame4p.pkl
deepdraughts-1.2.0.dist-info/LICENSE
deepdraughts-1.2.0.dist-info/METADATA
deepdraughts-1.2.0.dist-info/WHEEL
deepdraughts-1.2.0.dist-info/top_level.txt
deepdraughts-1.2.0.dist-info/RECORD
