Metadata-Version: 2.1
Name: deepdraughts
Version: 1.2.0
Summary: A library for playing draughts with AI
Home-page: https://github.com/EndlessLethe/DeepDraughts
Author: EndlessLethe
Author-email: zengsw_study@qq.com
License: GPLv2
Keywords: draughts MCTS checker deep neural network
Platform: UNKNOWN
Classifier: Development Status :: 3 - Alpha
Classifier: Programming Language :: Python :: 3
Classifier: Programming Language :: Python :: 3.6
Classifier: License :: OSI Approved :: GNU General Public License v2 (GPLv2)
Requires-Python: >=3.6
License-File: LICENSE
Requires-Dist: numpy (<1.20.0,>=1.17.0)
Requires-Dist: pygame (>=2.1.0)
Requires-Dist: requests (>=2.24.0)
Requires-Dist: torch (<=1.10.0,>=1.6.0)
Requires-Dist: tensorboardX (>=2.4)
